{
  "episodes": [
    {
      "id": "cw_1",
      "season": 2,
      "episode": 1,
      "air_code": "216",
      "title": "Cat and Mouse",
      "vitality": "skippable",
      "quality": "good",
      "notes": "",
      "tags": [
        "anakin-skywalker",
        "obi-wan-kenobi",
        "admiral-yularen",
        "admiral-trench",
        "christophsis",
        "bail-organa"
      ],
      "release_date": "2010-02-26",
      "release_year": 2010,
      "timeline_position": "22 BBY"
    },
    {
      "id": "cw_2",
      "season": 1,
      "episode": 2,
      "air_code": "116",
      "title": "Hidden Enemy",
      "vitality": "skippable",
      "quality": "good",
      "notes": "",
      "release_date": "2008-09-26",
      "release_year": 2008,
      "timeline_position": "22 BBY"
    },
    {
      "id": "cw_T",
      "season": "Film",
      "episode": "T",
      "air_code": "T",
      "title": "The Clone Wars (Theatrical Release)",
      "vitality": "vital",
      "quality": "bad",
      "notes": "Theatrical film",
      "tags": [
        "ahsoka"
      ],
      "release_date": "2008-08-15",
      "release_year": 2008,
      "timeline_position": "22 BBY"
    },
    {
      "id": "cw_3",
      "season": 3,
      "episode": 3,
      "air_code": "301",
      "title": "Clone Cadets",
      "vitality": "skippable",
      "quality": "good",
      "notes": "",
      "release_date": "2010-09-17",
      "release_year": 2010,
      "timeline_position": "22 BBY"
    },
    {
      "id": "cw_4",
      "season": 3,
      "episode": 4,
      "air_code": "303",
      "title": "Supply Lines",
      "vitality": "skippable",
      "quality": "bad",
      "notes": "",
      "release_date": "2010-10-01",
      "release_year": 2010,
      "timeline_position": "22 BBY"
    },
    {
      "id": "cw_5",
      "season": 1,
      "episode": 5,
      "air_code": "101",
      "title": "Ambush",
      "vitality": "skippable",
      "quality": "good",
      "notes": "",
      "release_date": "2008-10-03",
      "release_year": 2008,
      "timeline_position": "22 BBY"
    },
    {
      "id": "cw_6",
      "season": 1,
      "episode": 6,
      "air_code": "102",
      "title": "Rising Malevolence",
      "vitality": "skippable",
      "quality": "good",
      "notes": "",
      "release_date": "2008-10-03",
      "release_year": 2008,
      "timeline_position": "22 BBY"
    },
    {
      "id": "cw_7",
      "season": 1,
      "episode": 7,
      "air_code": "103",
      "title": "Shadow of Malevolence",
      "vitality": "skippable",
      "quality": "good",
      "notes": "",
      "release_date": "2008-10-10",
      "release_year": 2008,
      "timeline_position": "22 BBY"
    },
    {
      "id": "cw_8",
      "season": 1,
      "episode": 8,
      "air_code": "104",
      "title": "Destroy Malevolence",
      "vitality": "skippable",
      "quality": "good",
      "notes": "",
      "release_date": "2008-10-17",
      "release_year": 2008,
      "timeline_position": "22 BBY"
    },
    {
      "id": "cw_9",
      "season": 1,
      "episode": 9,
      "air_code": "105",
      "title": "Rookies",
      "vitality": "skippable",
      "quality": "good",
      "notes": "",
      "release_date": "2008-10-24",
      "release_year": 2008,
      "timeline_position": "22 BBY"
    },
    {
      "id": "cw_10",
      "season": 1,
      "episode": 10,
      "air_code": "106",
      "title": "Downfall of a Droid",
      "vitality": "skippable",
      "quality": "good",
      "notes": "",
      "release_date": "2008-10-31",
      "release_year": 2008,
      "timeline_position": "22 BBY"
    },
    {
      "id": "cw_11",
      "season": 1,
      "episode": 11,
      "air_code": "107",
      "title": "Duel of the Droids",
      "vitality": "skippable",
      "quality": "good",
      "notes": "",
      "release_date": "2008-11-07",
      "release_year": 2008,
      "timeline_position": "22 BBY"
    },
    {
      "id": "cw_12",
      "season": 1,
      "episode": 12,
      "air_code": "108",
      "title": "Bombad Jedi",
      "vitality": "skippable",
      "quality": "meh",
      "notes": "",
      "release_date": "2008-11-14",
      "release_year": 2008,
      "timeline_position": "22 BBY"
    },
    {
      "id": "cw_13",
      "season": 1,
      "episode": 13,
      "air_code": "109",
      "title": "Cloak of Darkness",
      "vitality": "skippable",
      "quality": "good",
      "notes": "",
      "release_date": "2008-12-19",
      "release_year": 2008,
      "timeline_position": "22 BBY"
    },
    {
      "id": "cw_14",
      "season": 1,
      "episode": 14,
      "air_code": "110",
      "title": "Lair of Grievous",
      "vitality": "skippable",
      "quality": "good",
      "notes": "",
      "release_date": "2008-12-05",
      "release_year": 2008,
      "timeline_position": "22 BBY"
    },
    {
      "id": "cw_15",
      "season": 1,
      "episode": 15,
      "air_code": "111",
      "title": "Dooku Captured",
      "vitality": null,
      "quality": null,
      "notes": "",
      "release_date": "2008-12-12",
      "release_year": 2008,
      "timeline_position": "22 BBY"
    },
    {
      "id": "cw_16",
      "season": 1,
      "episode": 16,
      "air_code": "112",
      "title": "The Gungan General",
      "vitality": null,
      "quality": null,
      "notes": "",
      "release_date": "2008-11-14",
      "release_year": 2008,
      "timeline_position": "22 BBY"
    },
    {
      "id": "cw_17",
      "season": 1,
      "episode": 17,
      "air_code": "113",
      "title": "Jedi Crash",
      "vitality": null,
      "quality": null,
      "notes": "",
      "release_date": "2009-01-09",
      "release_year": 2009,
      "timeline_position": "22 BBY"
    },
    {
      "id": "cw_18",
      "season": 1,
      "episode": 18,
      "air_code": "114",
      "title": "Defenders of Peace",
      "vitality": null,
      "quality": null,
      "notes": "",
      "release_date": "2009-01-16",
      "release_year": 2009,
      "timeline_position": "22 BBY"
    },
    {
      "id": "cw_19",
      "season": 1,
      "episode": 19,
      "air_code": "115",
      "title": "Trespass",
      "vitality": null,
      "quality": null,
      "notes": "",
      "release_date": "2009-01-23",
      "release_year": 2009,
      "timeline_position": "22 BBY"
    },
    {
      "id": "cw_20",
      "season": 1,
      "episode": 20,
      "air_code": "117",
      "title": "Blue Shadow Virus",
      "vitality": null,
      "quality": null,
      "notes": "",
      "release_date": "2009-03-20",
      "release_year": 2009,
      "timeline_position": "22 BBY"
    },
    {
      "id": "cw_21",
      "season": 1,
      "episode": 21,
      "air_code": "118",
      "title": "Mystery of a Thousand Moons",
      "vitality": null,
      "quality": null,
      "notes": "",
      "release_date": "2009-03-27",
      "release_year": 2009,
      "timeline_position": "22 BBY"
    },
    {
      "id": "cw_22",
      "season": 1,
      "episode": 22,
      "air_code": "119",
      "title": "Storm over Ryloth",
      "vitality": null,
      "quality": null,
      "notes": "",
      "release_date": "2009-04-03",
      "release_year": 2009,
      "timeline_position": "22 BBY"
    },
    {
      "id": "cw_23",
      "season": 1,
      "episode": 23,
      "air_code": "120",
      "title": "Innocents of Ryloth",
      "vitality": null,
      "quality": null,
      "notes": "",
      "release_date": "2009-04-10",
      "release_year": 2009,
      "timeline_position": "22 BBY"
    },
    {
      "id": "cw_24",
      "season": 1,
      "episode": 24,
      "air_code": "121",
      "title": "Liberty on Ryloth",
      "vitality": null,
      "quality": null,
      "notes": "",
      "release_date": "2009-04-17",
      "release_year": 2009,
      "timeline_position": "22 BBY"
    },
    {
      "id": "cw_25",
      "season": 2,
      "episode": 25,
      "air_code": "201",
      "title": "Holocron Heist",
      "vitality": null,
      "quality": null,
      "notes": "",
      "release_date": "2009-10-02",
      "release_year": 2009,
      "timeline_position": "21 BBY"
    },
    {
      "id": "cw_26",
      "season": 2,
      "episode": 26,
      "air_code": "202",
      "title": "Cargo of Doom",
      "vitality": null,
      "quality": null,
      "notes": "",
      "release_date": "2009-10-09",
      "release_year": 2009,
      "timeline_position": "21 BBY"
    },
    {
      "id": "cw_27",
      "season": 2,
      "episode": 27,
      "air_code": "203",
      "title": "Children of the Force",
      "vitality": null,
      "quality": null,
      "notes": "",
      "release_date": "2009-10-16",
      "release_year": 2009,
      "timeline_position": "21 BBY"
    },
    {
      "id": "cw_28",
      "season": 2,
      "episode": 28,
      "air_code": "217",
      "title": "Bounty Hunters",
      "vitality": null,
      "quality": null,
      "notes": "",
      "release_date": "2010-03-05",
      "release_year": 2010,
      "timeline_position": "21 BBY"
    },
    {
      "id": "cw_29",
      "season": 2,
      "episode": 29,
      "air_code": "218",
      "title": "The Zillo Beast",
      "vitality": null,
      "quality": null,
      "notes": "",
      "release_date": "2010-04-02",
      "release_year": 2010,
      "timeline_position": "21 BBY"
    },
    {
      "id": "cw_30",
      "season": 2,
      "episode": 30,
      "air_code": "219",
      "title": "The Zillo Beast Strikes Back",
      "vitality": null,
      "quality": null,
      "notes": "",
      "release_date": "2010-04-09",
      "release_year": 2010,
      "timeline_position": "21 BBY"
    },
    {
      "id": "cw_31",
      "season": 2,
      "episode": 31,
      "air_code": "204",
      "title": "Senate Spy",
      "vitality": null,
      "quality": null,
      "notes": "",
      "release_date": "2009-10-30",
      "release_year": 2009,
      "timeline_position": "21 BBY"
    },
    {
      "id": "cw_32",
      "season": 2,
      "episode": 32,
      "air_code": "205",
      "title": "Landing at Point Rain",
      "vitality": null,
      "quality": null,
      "notes": "",
      "release_date": "2009-11-06",
      "release_year": 2009,
      "timeline_position": "21 BBY"
    },
    {
      "id": "cw_33",
      "season": 2,
      "episode": 33,
      "air_code": "206",
      "title": "Weapons Factory",
      "vitality": null,
      "quality": null,
      "notes": "",
      "release_date": "2009-11-13",
      "release_year": 2009,
      "timeline_position": "21 BBY"
    },
    {
      "id": "cw_34",
      "season": 2,
      "episode": 34,
      "air_code": "207",
      "title": "Legacy of Terror",
      "vitality": null,
      "quality": null,
      "notes": "",
      "release_date": "2009-11-20",
      "release_year": 2009,
      "timeline_position": "21 BBY"
    },
    {
      "id": "cw_35",
      "season": 2,
      "episode": 35,
      "air_code": "208",
      "title": "Brain Invaders",
      "vitality": null,
      "quality": null,
      "notes": "",
      "release_date": "2009-12-04",
      "release_year": 2009,
      "timeline_position": "21 BBY"
    },
    {
      "id": "cw_36",
      "season": 2,
      "episode": 36,
      "air_code": "209",
      "title": "Grievous Intrigue",
      "vitality": null,
      "quality": null,
      "notes": "",
      "release_date": "2009-12-11",
      "release_year": 2009,
      "timeline_position": "21 BBY"
    },
    {
      "id": "cw_37",
      "season": 2,
      "episode": 37,
      "air_code": "210",
      "title": "The Deserter",
      "vitality": null,
      "quality": null,
      "notes": "",
      "release_date": "2010-01-01",
      "release_year": 2010,
      "timeline_position": "21 BBY"
    },
    {
      "id": "cw_38",
      "season": 2,
      "episode": 38,
      "air_code": "211",
      "title": "Lightsaber Lost",
      "vitality": null,
      "quality": null,
      "notes": "",
      "release_date": "2010-01-08",
      "release_year": 2010,
      "timeline_position": "21 BBY"
    },
    {
      "id": "cw_39",
      "season": 2,
      "episode": 39,
      "air_code": "212",
      "title": "The Mandalore Plot",
      "vitality": null,
      "quality": null,
      "notes": "",
      "release_date": "2010-01-22",
      "release_year": 2010,
      "timeline_position": "21 BBY"
    },
    {
      "id": "cw_40",
      "season": 2,
      "episode": 40,
      "air_code": "213",
      "title": "Voyage of Temptation",
      "vitality": null,
      "quality": null,
      "notes": "",
      "release_date": "2010-01-29",
      "release_year": 2010,
      "timeline_position": "21 BBY"
    },
    {
      "id": "cw_41",
      "season": 2,
      "episode": 41,
      "air_code": "214",
      "title": "Duchess of Mandalore",
      "vitality": null,
      "quality": null,
      "notes": "",
      "release_date": "2010-02-05",
      "release_year": 2010,
      "timeline_position": "21 BBY"
    },
    {
      "id": "cw_42",
      "season": 2,
      "episode": 42,
      "air_code": "220",
      "title": "Death Trap",
      "vitality": null,
      "quality": null,
      "notes": "",
      "release_date": "2010-04-23",
      "release_year": 2010,
      "timeline_position": "21 BBY"
    },
    {
      "id": "cw_43",
      "season": 2,
      "episode": 43,
      "air_code": "221",
      "title": "R2 Come Home",
      "vitality": null,
      "quality": null,
      "notes": "",
      "release_date": "2010-04-30",
      "release_year": 2010,
      "timeline_position": "21 BBY"
    },
    {
      "id": "cw_44",
      "season": 2,
      "episode": 44,
      "air_code": "222",
      "title": "Lethal Trackdown",
      "vitality": null,
      "quality": null,
      "notes": "",
      "release_date": "2010-05-07",
      "release_year": 2010,
      "timeline_position": "21 BBY"
    },
    {
      "id": "cw_45",
      "season": 3,
      "episode": 45,
      "air_code": "305",
      "title": "Corruption",
      "vitality": null,
      "quality": null,
      "notes": "",
      "release_date": "2010-10-15",
      "release_year": 2010,
      "timeline_position": "21 BBY"
    },
    {
      "id": "cw_46",
      "season": 3,
      "episode": 46,
      "air_code": "306",
      "title": "The Academy",
      "vitality": null,
      "quality": null,
      "notes": "",
      "release_date": "2010-10-22",
      "release_year": 2010,
      "timeline_position": "21 BBY"
    },
    {
      "id": "cw_47",
      "season": 3,
      "episode": 47,
      "air_code": "307",
      "title": "Assassin",
      "vitality": null,
      "quality": null,
      "notes": "",
      "release_date": "2010-10-29",
      "release_year": 2010,
      "timeline_position": "21 BBY"
    },
    {
      "id": "cw_48",
      "season": 3,
      "episode": 48,
      "air_code": "302",
      "title": "ARC Troopers",
      "vitality": null,
      "quality": null,
      "notes": "",
      "release_date": "2010-09-24",
      "release_year": 2010,
      "timeline_position": "21 BBY"
    },
    {
      "id": "cw_49",
      "season": 3,
      "episode": 49,
      "air_code": "304",
      "title": "Sphere of Influence",
      "vitality": null,
      "quality": null,
      "notes": "",
      "release_date": "2010-10-08",
      "release_year": 2010,
      "timeline_position": "21 BBY"
    },
    {
      "id": "cw_50",
      "season": 3,
      "episode": 50,
      "air_code": "308",
      "title": "Evil Plans",
      "vitality": null,
      "quality": null,
      "notes": "",
      "release_date": "2010-11-05",
      "release_year": 2010,
      "timeline_position": "21 BBY"
    },
    {
      "id": "cw_51",
      "season": 1,
      "episode": 51,
      "air_code": "122",
      "title": "Hostage Crisis",
      "vitality": null,
      "quality": null,
      "notes": "",
      "release_date": "2009-03-20",
      "release_year": 2009,
      "timeline_position": "22 BBY"
    },
    {
      "id": "cw_52",
      "season": 3,
      "episode": 52,
      "air_code": "309",
      "title": "Hunt for Ziro",
      "vitality": null,
      "quality": null,
      "notes": "",
      "release_date": "2010-11-12",
      "release_year": 2010,
      "timeline_position": "21 BBY"
    },
    {
      "id": "cw_53",
      "season": 3,
      "episode": 53,
      "air_code": "310",
      "title": "Heroes on Both Sides",
      "vitality": null,
      "quality": null,
      "notes": "",
      "release_date": "2010-11-19",
      "release_year": 2010,
      "timeline_position": "21 BBY"
    },
    {
      "id": "cw_54",
      "season": 3,
      "episode": 54,
      "air_code": "311",
      "title": "Pursuit of Peace",
      "vitality": null,
      "quality": null,
      "notes": "",
      "release_date": "2010-11-19",
      "release_year": 2010,
      "timeline_position": "21 BBY"
    },
    {
      "id": "cw_55",
      "season": 2,
      "episode": 55,
      "air_code": "215",
      "title": "Senate Murders",
      "vitality": null,
      "quality": null,
      "notes": "",
      "release_date": "2010-02-19",
      "release_year": 2010,
      "timeline_position": "21 BBY"
    },
    {
      "id": "cw_56",
      "season": 3,
      "episode": 56,
      "air_code": "312",
      "title": "Nightsisters",
      "vitality": null,
      "quality": null,
      "notes": "",
      "release_date": "2011-01-07",
      "release_year": 2011,
      "timeline_position": "21 BBY"
    },
    {
      "id": "cw_57",
      "season": 3,
      "episode": 57,
      "air_code": "313",
      "title": "Monster",
      "vitality": null,
      "quality": null,
      "notes": "",
      "release_date": "2011-01-14",
      "release_year": 2011,
      "timeline_position": "21 BBY"
    },
    {
      "id": "cw_58",
      "season": 3,
      "episode": 58,
      "air_code": "314",
      "title": "Witches of the Mist",
      "vitality": null,
      "quality": null,
      "notes": "",
      "release_date": "2011-01-21",
      "release_year": 2011,
      "timeline_position": "21 BBY"
    },
    {
      "id": "cw_59",
      "season": 3,
      "episode": 59,
      "air_code": "315",
      "title": "Overlords",
      "vitality": null,
      "quality": null,
      "notes": "",
      "release_date": "2011-01-28",
      "release_year": 2011,
      "timeline_position": "21 BBY"
    },
    {
      "id": "cw_60",
      "season": 3,
      "episode": 60,
      "air_code": "316",
      "title": "Altar of Mortis",
      "vitality": null,
      "quality": null,
      "notes": "",
      "release_date": "2011-02-04",
      "release_year": 2011,
      "timeline_position": "21 BBY"
    },
    {
      "id": "cw_61",
      "season": 3,
      "episode": 61,
      "air_code": "317",
      "title": "Ghosts of Mortis",
      "vitality": null,
      "quality": null,
      "notes": "",
      "release_date": "2011-02-11",
      "release_year": 2011,
      "timeline_position": "21 BBY"
    },
    {
      "id": "cw_62",
      "season": 3,
      "episode": 62,
      "air_code": "318",
      "title": "The Citadel",
      "vitality": null,
      "quality": null,
      "notes": "",
      "release_date": "2011-02-18",
      "release_year": 2011,
      "timeline_position": "21 BBY"
    },
    {
      "id": "cw_63",
      "season": 3,
      "episode": 63,
      "air_code": "319",
      "title": "Counter Attack",
      "vitality": null,
      "quality": null,
      "notes": "",
      "release_date": "2011-02-25",
      "release_year": 2011,
      "timeline_position": "21 BBY"
    },
    {
      "id": "cw_64",
      "season": 3,
      "episode": 64,
      "air_code": "320",
      "title": "Citadel Rescue",
      "vitality": null,
      "quality": null,
      "notes": "",
      "release_date": "2011-03-04",
      "release_year": 2011,
      "timeline_position": "21 BBY"
    },
    {
      "id": "cw_65",
      "season": 3,
      "episode": 65,
      "air_code": "321",
      "title": "Padawan Lost",
      "vitality": null,
      "quality": null,
      "notes": "",
      "release_date": "2011-03-25",
      "release_year": 2011,
      "timeline_position": "20 BBY"
    },
    {
      "id": "cw_66",
      "season": 3,
      "episode": 66,
      "air_code": "322",
      "title": "Wookiee Hunt",
      "vitality": null,
      "quality": null,
      "notes": "",
      "release_date": "2011-04-01",
      "release_year": 2011,
      "timeline_position": "20 BBY"
    },
    {
      "id": "cw_67",
      "season": 4,
      "episode": 67,
      "air_code": "401",
      "title": "Water War",
      "vitality": null,
      "quality": null,
      "notes": "",
      "release_date": "2011-09-16",
      "release_year": 2011,
      "timeline_position": "20 BBY"
    },
    {
      "id": "cw_68",
      "season": 4,
      "episode": 68,
      "air_code": "402",
      "title": "Gungan Attack",
      "vitality": null,
      "quality": null,
      "notes": "",
      "release_date": "2011-09-16",
      "release_year": 2011,
      "timeline_position": "20 BBY"
    },
    {
      "id": "cw_69",
      "season": 4,
      "episode": 69,
      "air_code": "403",
      "title": "Prisoners",
      "vitality": null,
      "quality": null,
      "notes": "",
      "release_date": "2011-09-23",
      "release_year": 2011,
      "timeline_position": "20 BBY"
    },
    {
      "id": "cw_70",
      "season": 4,
      "episode": 70,
      "air_code": "404",
      "title": "Shadow Warrior",
      "vitality": null,
      "quality": null,
      "notes": "",
      "release_date": "2011-09-30",
      "release_year": 2011,
      "timeline_position": "20 BBY"
    },
    {
      "id": "cw_71",
      "season": 4,
      "episode": 71,
      "air_code": "405",
      "title": "Mercy Mission",
      "vitality": null,
      "quality": null,
      "notes": "",
      "release_date": "2011-10-07",
      "release_year": 2011,
      "timeline_position": "20 BBY"
    },
    {
      "id": "cw_72",
      "season": 4,
      "episode": 72,
      "air_code": "406",
      "title": "Nomad Droids",
      "vitality": null,
      "quality": null,
      "notes": "",
      "release_date": "2011-10-14",
      "release_year": 2011,
      "timeline_position": "20 BBY"
    },
    {
      "id": "cw_73",
      "season": 4,
      "episode": 73,
      "air_code": "407",
      "title": "Darkness on Umbara",
      "vitality": null,
      "quality": null,
      "notes": "",
      "release_date": "2011-10-28",
      "release_year": 2011,
      "timeline_position": "20 BBY"
    },
    {
      "id": "cw_74",
      "season": 4,
      "episode": 74,
      "air_code": "408",
      "title": "The General",
      "vitality": null,
      "quality": null,
      "notes": "",
      "release_date": "2011-11-04",
      "release_year": 2011,
      "timeline_position": "20 BBY"
    },
    {
      "id": "cw_75",
      "season": 4,
      "episode": 75,
      "air_code": "409",
      "title": "Plan of Dissent",
      "vitality": null,
      "quality": null,
      "notes": "",
      "release_date": "2011-11-11",
      "release_year": 2011,
      "timeline_position": "20 BBY"
    },
    {
      "id": "cw_76",
      "season": 4,
      "episode": 76,
      "air_code": "410",
      "title": "Carnage of Krell",
      "vitality": null,
      "quality": null,
      "notes": "",
      "release_date": "2011-11-18",
      "release_year": 2011,
      "timeline_position": "20 BBY"
    },
    {
      "id": "cw_77",
      "season": 4,
      "episode": 77,
      "air_code": "411",
      "title": "Kidnapped",
      "vitality": null,
      "quality": null,
      "notes": "",
      "release_date": "2011-11-25",
      "release_year": 2011,
      "timeline_position": "20 BBY"
    },
    {
      "id": "cw_78",
      "season": 4,
      "episode": 78,
      "air_code": "412",
      "title": "Slaves of the Republic",
      "vitality": null,
      "quality": null,
      "notes": "",
      "release_date": "2011-12-02",
      "release_year": 2011,
      "timeline_position": "20 BBY"
    },
    {
      "id": "cw_79",
      "season": 4,
      "episode": 79,
      "air_code": "413",
      "title": "Escape from Kadavo",
      "vitality": null,
      "quality": null,
      "notes": "",
      "release_date": "2011-12-09",
      "release_year": 2011,
      "timeline_position": "20 BBY"
    },
    {
      "id": "cw_80",
      "season": 4,
      "episode": 80,
      "air_code": "414",
      "title": "A Friend In Need",
      "vitality": null,
      "quality": null,
      "notes": "",
      "release_date": "2012-01-13",
      "release_year": 2012,
      "timeline_position": "20 BBY"
    },
    {
      "id": "cw_81",
      "season": 4,
      "episode": 81,
      "air_code": "415",
      "title": "Deception",
      "vitality": null,
      "quality": null,
      "notes": "",
      "release_date": "2012-01-20",
      "release_year": 2012,
      "timeline_position": "20 BBY"
    },
    {
      "id": "cw_82",
      "season": 4,
      "episode": 82,
      "air_code": "416",
      "title": "Friends and Enemies",
      "vitality": null,
      "quality": null,
      "notes": "",
      "release_date": "2012-01-27",
      "release_year": 2012,
      "timeline_position": "20 BBY"
    },
    {
      "id": "cw_83",
      "season": 4,
      "episode": 83,
      "air_code": "417",
      "title": "The Box",
      "vitality": null,
      "quality": null,
      "notes": "",
      "release_date": "2012-02-03",
      "release_year": 2012,
      "timeline_position": "20 BBY"
    },
    {
      "id": "cw_84",
      "season": 4,
      "episode": 84,
      "air_code": "418",
      "title": "Crisis on Naboo",
      "vitality": null,
      "quality": null,
      "notes": "",
      "release_date": "2012-02-10",
      "release_year": 2012,
      "timeline_position": "20 BBY"
    },
    {
      "id": "cw_85",
      "season": 4,
      "episode": 85,
      "air_code": "419",
      "title": "Massacre",
      "vitality": null,
      "quality": null,
      "notes": "",
      "release_date": "2012-02-24",
      "release_year": 2012,
      "timeline_position": "20 BBY"
    },
    {
      "id": "cw_86",
      "season": 4,
      "episode": 86,
      "air_code": "420",
      "title": "Bounty",
      "vitality": null,
      "quality": null,
      "notes": "",
      "release_date": "2012-03-02",
      "release_year": 2012,
      "timeline_position": "20 BBY"
    },
    {
      "id": "cw_87",
      "season": 4,
      "episode": 87,
      "air_code": "421",
      "title": "Brothers",
      "vitality": null,
      "quality": null,
      "notes": "",
      "release_date": "2012-03-09",
      "release_year": 2012,
      "timeline_position": "20 BBY"
    },
    {
      "id": "cw_88",
      "season": 4,
      "episode": 88,
      "air_code": "422",
      "title": "Revenge",
      "vitality": null,
      "quality": null,
      "notes": "",
      "release_date": "2012-03-16",
      "release_year": 2012,
      "timeline_position": "20 BBY"
    },
    {
      "id": "cw_89",
      "season": 5,
      "episode": 89,
      "air_code": "502",
      "title": "A War on Two Fronts",
      "vitality": null,
      "quality": null,
      "notes": "",
      "release_date": "2012-10-06",
      "release_year": 2012,
      "timeline_position": "20 BBY"
    },
    {
      "id": "cw_90",
      "season": 5,
      "episode": 90,
      "air_code": "503",
      "title": "Front Runners",
      "vitality": null,
      "quality": null,
      "notes": "",
      "release_date": "2012-10-13",
      "release_year": 2012,
      "timeline_position": "20 BBY"
    },
    {
      "id": "cw_91",
      "season": 5,
      "episode": 91,
      "air_code": "504",
      "title": "The Soft War",
      "vitality": null,
      "quality": null,
      "notes": "",
      "release_date": "2012-10-20",
      "release_year": 2012,
      "timeline_position": "20 BBY"
    },
    {
      "id": "cw_92",
      "season": 5,
      "episode": 92,
      "air_code": "505",
      "title": "Tipping Points",
      "vitality": null,
      "quality": null,
      "notes": "",
      "release_date": "2012-10-27",
      "release_year": 2012,
      "timeline_position": "20 BBY"
    },
    {
      "id": "cw_93",
      "season": 5,
      "episode": 93,
      "air_code": "506",
      "title": "The Gathering",
      "vitality": null,
      "quality": null,
      "notes": "",
      "release_date": "2012-11-03",
      "release_year": 2012,
      "timeline_position": "20 BBY"
    },
    {
      "id": "cw_94",
      "season": 5,
      "episode": 94,
      "air_code": "507",
      "title": "A Test of Strength",
      "vitality": null,
      "quality": null,
      "notes": "",
      "release_date": "2012-11-10",
      "release_year": 2012,
      "timeline_position": "20 BBY"
    },
    {
      "id": "cw_95",
      "season": 5,
      "episode": 95,
      "air_code": "508",
      "title": "Bound for Rescue",
      "vitality": null,
      "quality": null,
      "notes": "",
      "release_date": "2012-11-17",
      "release_year": 2012,
      "timeline_position": "20 BBY"
    },
    {
      "id": "cw_96",
      "season": 5,
      "episode": 96,
      "air_code": "509",
      "title": "A Necessary Bond",
      "vitality": null,
      "quality": null,
      "notes": "",
      "release_date": "2012-11-24",
      "release_year": 2012,
      "timeline_position": "20 BBY"
    },
    {
      "id": "cw_97",
      "season": 5,
      "episode": 97,
      "air_code": "510",
      "title": "Secret Weapons",
      "vitality": null,
      "quality": null,
      "notes": "",
      "release_date": "2012-12-01",
      "release_year": 2012,
      "timeline_position": "20 BBY"
    },
    {
      "id": "cw_98",
      "season": 5,
      "episode": 98,
      "air_code": "511",
      "title": "A Sunny Day in the Void",
      "vitality": null,
      "quality": null,
      "notes": "",
      "release_date": "2012-12-08",
      "release_year": 2012,
      "timeline_position": "20 BBY"
    },
    {
      "id": "cw_99",
      "season": 5,
      "episode": 99,
      "air_code": "512",
      "title": "Missing in Action",
      "vitality": null,
      "quality": null,
      "notes": "",
      "release_date": "2012-12-15",
      "release_year": 2012,
      "timeline_position": "20 BBY"
    },
    {
      "id": "cw_100",
      "season": 5,
      "episode": 100,
      "air_code": "513",
      "title": "Point of No Return",
      "vitality": null,
      "quality": null,
      "notes": "",
      "release_date": "2013-01-05",
      "release_year": 2013,
      "timeline_position": "20 BBY"
    },
    {
      "id": "cw_101",
      "season": 5,
      "episode": 101,
      "air_code": "501",
      "title": "Revival",
      "vitality": null,
      "quality": null,
      "notes": "",
      "release_date": "2012-09-29",
      "release_year": 2012,
      "timeline_position": "20 BBY"
    },
    {
      "id": "cw_102",
      "season": 5,
      "episode": 102,
      "air_code": "514",
      "title": "Eminence",
      "vitality": null,
      "quality": null,
      "notes": "",
      "release_date": "2013-01-12",
      "release_year": 2013,
      "timeline_position": "19 BBY"
    },
    {
      "id": "cw_103",
      "season": 5,
      "episode": 103,
      "air_code": "515",
      "title": "Shades of Reason",
      "vitality": null,
      "quality": null,
      "notes": "",
      "release_date": "2013-01-19",
      "release_year": 2013,
      "timeline_position": "19 BBY"
    },
    {
      "id": "cw_104",
      "season": 5,
      "episode": 104,
      "air_code": "516",
      "title": "The Lawless",
      "vitality": null,
      "quality": null,
      "notes": "",
      "release_date": "2013-01-26",
      "release_year": 2013,
      "timeline_position": "19 BBY"
    },
    {
      "id": "cw_105",
      "season": 5,
      "episode": 105,
      "air_code": "517",
      "title": "Sabotage",
      "vitality": null,
      "quality": null,
      "notes": "",
      "release_date": "2013-02-02",
      "release_year": 2013,
      "timeline_position": "19 BBY"
    },
    {
      "id": "cw_106",
      "season": 5,
      "episode": 106,
      "air_code": "518",
      "title": "The Jedi Who Knew Too Much",
      "vitality": null,
      "quality": null,
      "notes": "",
      "release_date": "2013-02-09",
      "release_year": 2013,
      "timeline_position": "19 BBY"
    },
    {
      "id": "cw_107",
      "season": 5,
      "episode": 107,
      "air_code": "519",
      "title": "To Catch a Jedi",
      "vitality": null,
      "quality": null,
      "notes": "",
      "release_date": "2013-02-16",
      "release_year": 2013,
      "timeline_position": "19 BBY"
    },
    {
      "id": "cw_108",
      "season": 5,
      "episode": 108,
      "air_code": "520",
      "title": "The Wrong Jedi",
      "vitality": null,
      "quality": null,
      "notes": "",
      "release_date": "2013-03-02",
      "release_year": 2013,
      "timeline_position": "19 BBY"
    },
    {
      "id": "cw_109",
      "season": 6,
      "episode": 109,
      "air_code": "601",
      "title": "The Unknown",
      "vitality": null,
      "quality": null,
      "notes": "",
      "release_date": "2014-03-07",
      "release_year": 2014,
      "timeline_position": "19 BBY"
    },
    {
      "id": "cw_110",
      "season": 6,
      "episode": 110,
      "air_code": "602",
      "title": "Conspiracy",
      "vitality": null,
      "quality": null,
      "notes": "",
      "release_date": "2014-03-07",
      "release_year": 2014,
      "timeline_position": "19 BBY"
    },
    {
      "id": "cw_111",
      "season": 6,
      "episode": 111,
      "air_code": "603",
      "title": "Fugitive",
      "vitality": null,
      "quality": null,
      "notes": "",
      "release_date": "2014-03-07",
      "release_year": 2014,
      "timeline_position": "19 BBY"
    },
    {
      "id": "cw_112",
      "season": 6,
      "episode": 112,
      "air_code": "604",
      "title": "Orders",
      "vitality": null,
      "quality": null,
      "notes": "",
      "release_date": "2014-03-07",
      "release_year": 2014,
      "timeline_position": "19 BBY"
    },
    {
      "id": "cw_113",
      "season": 6,
      "episode": 113,
      "air_code": "605",
      "title": "An Old Friend",
      "vitality": null,
      "quality": null,
      "notes": "",
      "release_date": "2014-03-07",
      "release_year": 2014,
      "timeline_position": "19 BBY"
    },
    {
      "id": "cw_114",
      "season": 6,
      "episode": 114,
      "air_code": "606",
      "title": "The Rise of Clovis",
      "vitality": null,
      "quality": null,
      "notes": "",
      "release_date": "2014-03-07",
      "release_year": 2014,
      "timeline_position": "19 BBY"
    },
    {
      "id": "cw_115",
      "season": 6,
      "episode": 115,
      "air_code": "607",
      "title": "Crisis at the Heart",
      "vitality": null,
      "quality": null,
      "notes": "",
      "release_date": "2014-03-07",
      "release_year": 2014,
      "timeline_position": "19 BBY"
    },
    {
      "id": "cw_116",
      "season": 6,
      "episode": 116,
      "air_code": "608",
      "title": "The Disappeared",
      "vitality": null,
      "quality": null,
      "notes": "",
      "release_date": "2014-03-07",
      "release_year": 2014,
      "timeline_position": "19 BBY"
    },
    {
      "id": "cw_117",
      "season": 6,
      "episode": 117,
      "air_code": "609",
      "title": "The Disappeared: Pt. II",
      "vitality": null,
      "quality": null,
      "notes": "",
      "release_date": "2014-03-07",
      "release_year": 2014,
      "timeline_position": "19 BBY"
    },
    {
      "id": "cw_118",
      "season": 6,
      "episode": 118,
      "air_code": "610",
      "title": "The Lost One",
      "vitality": null,
      "quality": null,
      "notes": "",
      "release_date": "2014-03-07",
      "release_year": 2014,
      "timeline_position": "19 BBY"
    },
    {
      "id": "cw_119",
      "season": 6,
      "episode": 119,
      "air_code": "611",
      "title": "Voices",
      "vitality": null,
      "quality": null,
      "notes": "",
      "release_date": "2014-03-07",
      "release_year": 2014,
      "timeline_position": "19 BBY"
    },
    {
      "id": "cw_120",
      "season": 6,
      "episode": 120,
      "air_code": "612",
      "title": "Destiny",
      "vitality": null,
      "quality": null,
      "notes": "",
      "release_date": "2014-03-07",
      "release_year": 2014,
      "timeline_position": "19 BBY"
    },
    {
      "id": "cw_121",
      "season": 6,
      "episode": 121,
      "air_code": "613",
      "title": "Sacrifice",
      "vitality": null,
      "quality": null,
      "notes": "",
      "release_date": "2014-03-07",
      "release_year": 2014,
      "timeline_position": "19 BBY"
    },
    {
      "id": "cw_122",
      "season": 7,
      "episode": 122,
      "air_code": "705",
      "title": "Gone with a Trace",
      "vitality": null,
      "quality": null,
      "notes": "",
      "release_date": "2020-03-20",
      "release_year": 2020,
      "timeline_position": "19 BBY"
    },
    {
      "id": "cw_123",
      "season": 7,
      "episode": 123,
      "air_code": "706",
      "title": "Deal No Deal",
      "vitality": null,
      "quality": null,
      "notes": "",
      "release_date": "2020-03-27",
      "release_year": 2020,
      "timeline_position": "19 BBY"
    },
    {
      "id": "cw_124",
      "season": 7,
      "episode": 124,
      "air_code": "707",
      "title": "Dangerous Debt",
      "vitality": null,
      "quality": null,
      "notes": "",
      "release_date": "2020-04-03",
      "release_year": 2020,
      "timeline_position": "19 BBY"
    },
    {
      "id": "cw_125",
      "season": 7,
      "episode": 125,
      "air_code": "708",
      "title": "Together Again",
      "vitality": null,
      "quality": null,
      "notes": "",
      "release_date": "2020-04-10",
      "release_year": 2020,
      "timeline_position": "19 BBY"
    },
    {
      "id": "cw_126",
      "season": 7,
      "episode": 126,
      "air_code": "701",
      "title": "The Bad Batch",
      "vitality": null,
      "quality": null,
      "notes": "",
      "release_date": "2020-02-21",
      "release_year": 2020,
      "timeline_position": "19 BBY"
    },
    {
      "id": "cw_127",
      "season": 7,
      "episode": 127,
      "air_code": "702",
      "title": "A Distant Echo",
      "vitality": null,
      "quality": null,
      "notes": "",
      "release_date": "2020-02-28",
      "release_year": 2020,
      "timeline_position": "19 BBY"
    },
    {
      "id": "cw_128",
      "season": 7,
      "episode": 128,
      "air_code": "703",
      "title": "On the Wings of Keeradaks",
      "vitality": null,
      "quality": null,
      "notes": "",
      "release_date": "2020-03-06",
      "release_year": 2020,
      "timeline_position": "19 BBY"
    },
    {
      "id": "cw_129",
      "season": 7,
      "episode": 129,
      "air_code": "704",
      "title": "Unfinished Business",
      "vitality": null,
      "quality": null,
      "notes": "",
      "release_date": "2020-03-13",
      "release_year": 2020,
      "timeline_position": "19 BBY"
    },
    {
      "id": "cw_130",
      "season": 7,
      "episode": 130,
      "air_code": "709",
      "title": "Old Friends Not Forgotten",
      "vitality": null,
      "quality": null,
      "notes": "",
      "release_date": "2020-04-17",
      "release_year": 2020,
      "timeline_position": "19 BBY"
    },
    {
      "id": "cw_131",
      "season": 7,
      "episode": 131,
      "air_code": "710",
      "title": "The Phantom Apprentice",
      "vitality": null,
      "quality": null,
      "notes": "",
      "release_date": "2020-04-24",
      "release_year": 2020,
      "timeline_position": "19 BBY"
    },
    {
      "id": "cw_132",
      "season": 7,
      "episode": 132,
      "air_code": "711",
      "title": "Shattered",
      "vitality": null,
      "quality": null,
      "notes": "",
      "release_date": "2020-05-01",
      "release_year": 2020,
      "timeline_position": "19 BBY"
    },
    {
      "id": "cw_133",
      "season": 7,
      "episode": 133,
      "air_code": "712",
      "title": "Victory and Death",
      "vitality": null,
      "quality": null,
      "notes": "",
      "release_date": "2020-05-04",
      "release_year": 2020,
      "timeline_position": "19 BBY"
    }
  ]
}
